pychatbgp/__init__.py
pychatbgp/get_rib.py
pychatbgp/get_rib_size.py
pychatbgp/get_updates.py
pychatbgp/get_updates_size.py
pychatbgp/get_vantage_points.py
pychatbgp-0.1.13.dist-info/LICENSE
pychatbgp-0.1.13.dist-info/METADATA
pychatbgp-0.1.13.dist-info/WHEEL
pychatbgp-0.1.13.dist-info/top_level.txt
pychatbgp-0.1.13.dist-info/RECORD
